odoo8_addon_mis_builder_demo-8.0.1.0.0-py2.7-nspkg.pth
odoo_addons/mis_builder_demo/__openerp__.py
odoo_addons/mis_builder_demo/mis.report.instance.csv
odoo_addons/mis_builder_demo/mis.report.csv
odoo_addons/mis_builder_demo/mis.report.instance.period.csv
odoo_addons/mis_builder_demo/mis.report.query.csv
odoo_addons/mis_builder_demo/__init__.py
odoo_addons/mis_builder_demo/README.rst
odoo_addons/mis_builder_demo/mis.report.kpi.csv
odoo8_addon_mis_builder_demo-8.0.1.0.0.dist-info/top_level.txt
odoo8_addon_mis_builder_demo-8.0.1.0.0.dist-info/WHEEL
odoo8_addon_mis_builder_demo-8.0.1.0.0.dist-info/RECORD
odoo8_addon_mis_builder_demo-8.0.1.0.0.dist-info/metadata.json
odoo8_addon_mis_builder_demo-8.0.1.0.0.dist-info/DESCRIPTION.rst
odoo8_addon_mis_builder_demo-8.0.1.0.0.dist-info/METADATA
odoo8_addon_mis_builder_demo-8.0.1.0.0.dist-info/namespace_packages.txt
